{
  "updatedAt": "2026-05-15T09:34:56.512Z",
  "createdAt": "2026-05-15T09:34:56.512Z",
  "id": "mFTXyr7bxaspffYI",
  "name": "0108_Noop_GitHub_Create_Triggered",
  "active": false,
  "isArchived": false,
  "nodes": [
    {
      "name": "Github Trigger",
      "type": "n8n-nodes-base.githubTrigger",
      "position": [
        450,
        300
      ],
      "webhookId": "52c5fe44-23ef-4903-b6ae-731edd36127e",
      "parameters": {
        "owner": "harshil1712",
        "events": [
          "issue_comment",
          "issues"
        ],
        "repository": "build-discord-bot",
        "authentication": "oAuth2"
      },
      "credentials": {
        "githubOAuth2Api": "GitHub Personal Credentials"
      },
      "typeVersion": 1,
      "id": "f48530a9-1db9-42f9-8429-d4daf09dd563"
    },
    {
      "name": "Github Trigger",
      "type": "n8n-nodes-base.githubTrigger",
      "position": [
        450,
        300
      ],
      "webhookId": "52c5fe44-23ef-4903-b6ae-731edd36127e",
      "parameters": {
        "owner": "harshil1712",
        "events": [
          "issue_comment",
          "issues"
        ],
        "repository": "build-discord-bot",
        "authentication": "oAuth2"
      },
      "credentials": {
        "githubOAuth2Api": {
          "id": null,
          "name": "GitHub Personal Credentials"
        }
      },
      "typeVersion": 1,
      "id": "2de16634-9966-4f6f-8f1c-c370bf058ef8"
    },
    {
      "name": "Switch",
      "type": "n8n-nodes-base.switch",
      "position": [
        650,
        300
      ],
      "parameters": {
        "rules": {
          "rules": [
            {
              "value2": "opened"
            },
            {
              "output": 1,
              "value2": "created"
            }
          ]
        },
        "value1": "={{$json[\"body\"][\"action\"]}}",
        "dataType": "string"
      },
      "typeVersion": 1,
      "id": "8317904a-dd3f-4b43-9b7a-f2031169021f"
    },
    {
      "name": "IF no assignee?",
      "type": "n8n-nodes-base.if",
      "position": [
        1050,
        150
      ],
      "parameters": {
        "conditions": {
          "number": [
            {
              "value1": "={{$json[\"body\"][\"issue\"][\"assignees\"].length}}",
              "operation": "equal"
            }
          ],
          "string": [
            {
              "value1": "={{$json[\"body\"][\"issue\"][\"body\"]}}",
              "value2": "/[a,A]ssign[\\w*\\s*]*me/gm",
              "operation": "regex"
            }
          ]
        }
      },
      "typeVersion": 1,
      "id": "4c5537af-8cd7-4cd7-bbaf-2abaff43181f"
    },
    {
      "name": "NoOp",
      "type": "n8n-nodes-base.noOp",
      "position": [
        1250,
        250
      ],
      "parameters": {},
      "typeVersion": 1,
      "id": "04cd31b0-e8e0-4b90-86ec-68594252141d"
    },
    {
      "name": "IF wants to work?",
      "type": "n8n-nodes-base.if",
      "position": [
        850,
        500
      ],
      "parameters": {
        "conditions": {
          "number": [],
          "string": [
            {
              "value1": "={{$json[\"body\"][\"comment\"][\"body\"]}}",
              "value2": "/[a,A]ssign[\\w*\\s*]*me/gm",
              "operation": "regex"
            }
          ]
        }
      },
      "typeVersion": 1,
      "id": "10016a05-8ced-420d-9722-31da99498393"
    },
    {
      "name": "IF not assigned?",
      "type": "n8n-nodes-base.if",
      "position": [
        1050,
        450
      ],
      "parameters": {
        "conditions": {
          "number": [
            {
              "value1": "={{$json[\"body\"][\"issue\"][\"assignees\"].length}}",
              "operation": "equal"
            }
          ],
          "string": []
        }
      },
      "typeVersion": 1,
      "id": "0c31eddb-8a03-48da-965e-ec5541f955e5"
    },
    {
      "name": "Assign Issue Creator",
      "type": "n8n-nodes-base.github",
      "position": [
        1250,
        50
      ],
      "parameters": {
        "owner": "={{$node[\"Switch\"].json[\"body\"][\"repository\"][\"owner\"][\"login\"]}}",
        "operation": "edit",
        "editFields": {
          "labels": [
            {
              "label": "assigned"
            }
          ],
          "assignees": [
            {
              "assignee": "={{$json.body.issue[\"user\"][\"login\"]}}"
            }
          ]
        },
        "repository": "={{$node[\"Switch\"].json[\"body\"][\"repository\"][\"name\"]}}",
        "issueNumber": "={{ $json[\"body\"][\"issue\"][\"number\"] }}",
        "authentication": "oAuth2"
      },
      "credentials": {
        "githubOAuth2Api": "GitHub@Harshil"
      },
      "typeVersion": 1,
      "id": "4795cbc1-f4bf-436b-9ef2-cebd7c6fdb9e",
      "webhookId": "8fd15c24-a711-4347-a68f-ba5f201f2ee2"
    },
    {
      "name": "Add Comment",
      "type": "n8n-nodes-base.github",
      "position": [
        1350,
        600
      ],
      "parameters": {
        "body": "=Hey @{{$json[\"body\"][\"comment\"][\"user\"][\"login\"]}},\n\nThis issue is already assigned to {{$json[\"body\"][\"issue\"][\"assignee\"][\"login\"]}} 🙂",
        "owner": "={{$json[\"body\"][\"repository\"][\"owner\"][\"login\"]}}",
        "operation": "createComment",
        "repository": "={{$json[\"body\"][\"repository\"][\"name\"]}}",
        "issueNumber": "={{$json[\"body\"][\"issue\"][\"number\"]}}",
        "authentication": "oAuth2"
      },
      "credentials": {
        "githubOAuth2Api": {
          "id": null,
          "name": "GitHub@Harshil"
        }
      },
      "typeVersion": 1,
      "id": "cf33feb7-daf1-49d0-ad29-f7693f79fc55",
      "webhookId": "1ac1fce0-3bd6-487f-b941-99753680015d"
    },
    {
      "name": "NoOp1",
      "type": "n8n-nodes-base.noOp",
      "position": [
        1050,
        650
      ],
      "parameters": {},
      "typeVersion": 1,
      "id": "434c981d-fc23-46d3-852d-feca46e65207"
    },
    {
      "name": "Assign Commenter",
      "type": "n8n-nodes-base.github",
      "position": [
        1350,
        400
      ],
      "parameters": {
        "owner": "={{$json[\"body\"][\"repository\"][\"owner\"][\"login\"]}}",
        "operation": "edit",
        "editFields": {
          "labels": [
            {
              "label": "assigned"
            }
          ],
          "assignees": [
            {
              "assignee": "={{$json[\"body\"][\"comment\"][\"user\"][\"login\"]}}"
            }
          ]
        },
        "repository": "={{$json[\"body\"][\"repository\"][\"name\"]}}",
        "issueNumber": "={{$json[\"body\"][\"issue\"][\"number\"]}}",
        "authentication": "oAuth2"
      },
      "credentials": {
        "githubOAuth2Api": {
          "id": null,
          "name": "GitHub@Harshil"
        }
      },
      "typeVersion": 1,
      "id": "1452bf59-9c21-4d27-a1b6-55d7fb1364a5",
      "webhookId": "ea48ef07-0d83-43c0-b467-25ff6c9dc411"
    }
  ],
  "connections": {
    "Switch": {
      "main": [
        [
          {
            "node": "IF no assignee?",
            "type": "main",
            "index": 0
          }
        ],
        [
          {
            "node": "IF wants to work?",
            "type": "main",
            "index": 0
          }
        ]
      ]
    },
    "Github Trigger": {
      "main": [
        [
          {
            "node": "Switch",
            "type": "main",
            "index": 0
          }
        ]
      ]
    },
    "IF no assignee?": {
      "main": [
        [
          {
            "node": "Assign Issue Creator",
            "type": "main",
            "index": 0
          }
        ],
        [
          {
            "node": "NoOp",
            "type": "main",
            "index": 0
          }
        ]
      ]
    },
    "IF not assigned?": {
      "main": [
        [
          {
            "node": "Assign Commenter",
            "type": "main",
            "index": 0
          }
        ],
        [
          {
            "node": "Add Comment",
            "type": "main",
            "index": 0
          }
        ]
      ]
    },
    "IF wants to work?": {
      "main": [
        [
          {
            "node": "IF not assigned?",
            "type": "main",
            "index": 0
          }
        ],
        [
          {
            "node": "NoOp1",
            "type": "main",
            "index": 0
          }
        ]
      ]
    }
  },
  "settings": {},
  "staticData": null,
  "meta": null,
  "pinData": null,
  "versionId": "3432a506-ffad-4d2f-91da-65dbd697e49d",
  "activeVersionId": null,
  "triggerCount": 0,
  "shared": [
    {
      "updatedAt": "2026-05-15T09:34:56.512Z",
      "createdAt": "2026-05-15T09:34:56.512Z",
      "role": "workflow:owner",
      "workflowId": "mFTXyr7bxaspffYI",
      "projectId": "HkDrNvwtLnIGtiR1"
    }
  ],
  "activeVersion": null,
  "tags": []
}